InduPack/__init__.py
InduPack/module1.py
InduPack/module2.py
InduPack-0.1.dist-info/LICENCE
InduPack-0.1.dist-info/METADATA
InduPack-0.1.dist-info/WHEEL
InduPack-0.1.dist-info/top_level.txt
InduPack-0.1.dist-info/RECORD
